pynock/__init__.py
pynock/pynock.py
pynock-1.2.1.dist-info/LICENSE
pynock-1.2.1.dist-info/METADATA
pynock-1.2.1.dist-info/WHEEL
pynock-1.2.1.dist-info/top_level.txt
pynock-1.2.1.dist-info/RECORD
