Metadata-Version: 2.1
Name: pynock
Version: 1.2.1
Summary: A proposed standard `NOCK` for a Parquet format that supports efficient distributed serialization of multiple kinds of graph technologies.
Home-page: https://github.com/DerwenAI/pynock
Author: Paco Nathan
Author-email: paco@derwen.ai
License: MIT
Keywords: CSV,Parquet,RDF,dataframe,graph data science,knowledge graph,labeled property graphs,open standard,openCypher,probabilistic graphs,semantic graphs,serialization,spreadsheet
Platform: UNKNOWN
Classifier: Programming Language :: Python :: 3
Classifier: License :: OSI Approved :: MIT License
Classifier: Operating System :: OS Independent
Classifier: Development Status :: 5 - Production/Stable
Classifier: Intended Audience :: Developers
Classifier: Intended Audience :: Information Technology
Classifier: Intended Audience :: Science/Research
Classifier: Topic :: Scientific/Engineering :: Artificial Intelligence
Classifier: Topic :: Scientific/Engineering :: Human Machine Interfaces
Classifier: Topic :: Scientific/Engineering :: Information Analysis
Classifier: Topic :: Software Development :: Testing
Classifier: Topic :: System :: Distributed Computing
Requires-Python: >=3.8
Requires-Dist: cloudpathlib (>=0.10)
Requires-Dist: icecream (>=2.1)
Requires-Dist: networkx (>=2.8.7)
Requires-Dist: pandas (>=1.4)
Requires-Dist: pyarrow (>=6.0)
Requires-Dist: pydantic (>=1.10)
Requires-Dist: rdflib (>=6.2)
Requires-Dist: typer[all] (>=0.6)
